pbshm/graphcomparison/__init__.py
pbshm/graphcomparison/backtracking.py
pbshm/graphcomparison/matrix.py
pbshm/graphcomparison/routes.py
pbshm/graphcomparison/templates/compare.html
pbshm/graphcomparison/templates/list-ie-models.html
pbshm/graphcomparison/templates/results.html
pbshm_network_mcs-0.1.1.dist-info/licenses/LICENSE
pbshm_network_mcs-0.1.1.dist-info/METADATA
pbshm_network_mcs-0.1.1.dist-info/WHEEL
pbshm_network_mcs-0.1.1.dist-info/top_level.txt
pbshm_network_mcs-0.1.1.dist-info/RECORD
