Metadata-Version: 2.4
Name: pbshm-network-mcs
Version: 0.1.1
Summary: PBSHM Graph Comparisons through Jaccard Index and Maximum Common Subgraph
Author: Julian Gosliga
Maintainer-email: Dan Brennan <d.s.brennan@sheffield.ac.uk>
License:                     GNU AFFERO GENERAL PUBLIC LICENSE
Project-URL: homepage, https://github.com/dynamics-research-group/ag-mcs
Classifier: License :: OSI Approved :: GNU Affero General Public License v3 or later (AGPLv3+)
Classifier: Programming Language :: Python :: 3
Classifier: Framework :: Flask
Requires-Python: >=3.8.10
License-File: LICENSE
Requires-Dist: pbshm-core==1.1.6
Requires-Dist: numpy==2.3.0
Requires-Dist: seaborn==0.13.2
Requires-Dist: matplotlib==3.10.3
Dynamic: license-file
